sofairfilter/__init__.py
sofairfilter/__main__.py
sofairfilter/config.yaml
sofairfilter/filter.py
sofairfilter/model_factory.py
sofairfilter/tokenizer_factory.py
sofairfilter-1.0.0.dist-info/METADATA
sofairfilter-1.0.0.dist-info/WHEEL
sofairfilter-1.0.0.dist-info/entry_points.txt
sofairfilter-1.0.0.dist-info/top_level.txt
sofairfilter-1.0.0.dist-info/RECORD
