Metadata-Version: 2.4
Name: sofairfilter
Version: 1.0.0
Summary: Tool for identifying candidate documents for software mention extraction.
Author: Martin Dočekal
Project-URL: Repository, https://github.com/SoFairOA/filter
Keywords: software mentions,filtering,candidate documents,text processing,NLP
Requires-Python: >=3.10
Requires-Dist: torch
Requires-Dist: classconfig
Requires-Dist: transformers
Requires-Dist: tqdm
Requires-Dist: bitsandbytes
